engine4/__init__.py
engine4/constants.py
engine4/engine4.py
engine4/exceptions.py
engine4/utils.py
engine4/version.py
engine4-0.0.2.dist-info/LICENSE
engine4-0.0.2.dist-info/METADATA
engine4-0.0.2.dist-info/WHEEL
engine4-0.0.2.dist-info/top_level.txt
engine4-0.0.2.dist-info/RECORD
