Metadata-Version: 2.1
Name: engine4
Version: 0.0.2
Summary: ENGINE4 API Wrapper
Home-page: https://github.com/robingenz/engine4-python
Author: Robin Genz
Author-email: mail@robingenz.dev
License: MIT
Project-URL: Documentation, https://docs.engine4.io/api
Project-URL: Github, https://github.com/robingenz/engine4-python
Classifier: Programming Language :: Python
Classifier: Programming Language :: Python :: 3
Classifier: Programming Language :: Python :: 3.6
Classifier: Programming Language :: Python :: 3.7
Classifier: Programming Language :: Python :: 3.8
Classifier: Programming Language :: Python :: 3.9
Requires-Python: >=3.6
License-File: LICENSE
Requires-Dist: requests
